smoothtables.py
smoothtables-1.0.0.dist-info/LICENSE.txt
smoothtables-1.0.0.dist-info/METADATA
smoothtables-1.0.0.dist-info/WHEEL
smoothtables-1.0.0.dist-info/top_level.txt
smoothtables-1.0.0.dist-info/RECORD
