Metadata-Version: 2.1
Name: smoothtables
Version: 1.0.0
Summary: A module to generate tables and panels with box drawing borders.
Home-page: https://github.com/lbaca/smoothtables
Author: Leandro Baca
Author-email: leandrobaca77@gmail.com
License: UNKNOWN
Keywords: table tables panel panels text box drawing
Platform: UNKNOWN
Classifier: Development Status :: 5 - Production/Stable
Classifier: Environment :: Console
Classifier: Intended Audience :: Developers
Classifier: Programming Language :: Python :: 3
Classifier: Programming Language :: Python :: 3.6
Classifier: Programming Language :: Python :: 3.7
Classifier: Programming Language :: Python :: 3.8
Classifier: Programming Language :: Python :: 3.9
Classifier: License :: OSI Approved :: MIT License
Classifier: Operating System :: OS Independent
Classifier: Topic :: Documentation
Classifier: Topic :: Printing
Classifier: Topic :: Software Development :: Libraries :: Python Modules
Classifier: Topic :: Text Processing :: General
Classifier: Topic :: Software Development
Requires-Python: ~=3.6
